CHANGELOG.rst
LICENSE
MANIFEST.in
README.rst
climos
setup.py
mosclient/__init__.py
mosclient/client.py
mosclient/shell.py
mosclient.egg-info/PKG-INFO
mosclient.egg-info/SOURCES.txt
mosclient.egg-info/dependency_links.txt
mosclient.egg-info/entry_points.txt
mosclient.egg-info/requires.txt
mosclient.egg-info/top_level.txt
mosclient/common/__init__.py
mosclient/common/client.py
mosclient/common/ec2utils.py
mosclient/common/setuputils.py
mosclient/common/utils.py
mosclient/common/xmltodict.py
mosclient/v1/__init__.py
mosclient/v1/client.py
mosclient/v1/shell.py
tools/pip-requires