Metadata-Version: 1.0
Name: mosclient
Version: 1.0.7
Summary: Client library for Meituan Cloud Platform EC2 API
Home-page: https://mos.meituan.com/document#sdk.html
Author: Meituan Open Services
Author-email: mos@meituan.com
License: UNKNOWN
Platform: UNKNOWN
Classifier: Development Status :: 4 - Beta
Classifier: Environment :: Console
Classifier: Intended Audience :: Developers
Classifier: Intended Audience :: Information Technology
Classifier: Operating System :: OS Independent
Classifier: Programming Language :: Python
